{
  "alerts": [],
  "global_error_alert_signatures": [
    "6803674106f6f9d2b46bf9ea06bc236f747006bd2ea0fdfd9d3fa557b4833754"
  ],
  "urls": {
    "https://maxireves.fr/?s=OP-17&post_type=product": {
      "consecutive_errors": 0,
      "last_checked_utc": "2026-06-20T15:57:46.247854+00:00",
      "last_error": "URLError(TimeoutError('timed out'))",
      "last_error_status": null,
      "last_error_utc": "2026-06-20T01:52:10.336160+00:00",
      "last_hash": "c2b84f4581fd91086fd1ea09191735da9182ac19e43e2838cc60c2c12a909a1f",
      "last_recovered_utc": "2026-06-20T02:01:11.031201+00:00",
      "last_status": 200
    },
    "https://maxireves.fr/?s=OP17&post_type=product": {
      "consecutive_errors": 0,
      "last_checked_utc": "2026-06-20T15:57:43.742706+00:00",
      "last_error": "URLError(TimeoutError('timed out'))",
      "last_error_status": null,
      "last_error_utc": "2026-06-20T01:51:47.490161+00:00",
      "last_hash": "fbb0360e97c18971125d47944c616457594c1dc0290610dc037d42d8c716057c",
      "last_recovered_utc": "2026-06-20T02:01:08.251220+00:00",
      "last_status": 200
    },
    "https://maxireves.fr/selection-jeux/jeux-de-cartes-tcg/one-piece-tcg/display-one-piece-tcg/": {
      "consecutive_errors": 0,
      "last_checked_utc": "2026-06-20T15:57:32.374066+00:00",
      "last_error": "URLError(TimeoutError('timed out'))",
      "last_error_status": null,
      "last_error_utc": "2026-06-20T01:50:59.083022+00:00",
      "last_hash": "7591ad2d4df92fc303c46763121dfe0146dc7032c10138fb9195214e30420d4c",
      "last_recovered_utc": "2026-06-20T02:00:56.671888+00:00",
      "last_status": 200
    },
    "https://maxireves.fr/selection-jeux/nouveautes-et-precommandes/": {
      "consecutive_errors": 0,
      "last_checked_utc": "2026-06-20T15:57:38.622040+00:00",
      "last_error": "URLError(TimeoutError('timed out'))",
      "last_error_status": null,
      "last_error_utc": "2026-06-20T01:51:23.199629+00:00",
      "last_hash": "5498666a897eed35aeb27672231ff125818c99f273249d020ac9ffd9861eb440",
      "last_recovered_utc": "2026-06-20T02:01:02.519525+00:00",
      "last_status": 200
    }
  }
}
